easy_tornado/__init__.py
easy_tornado/compat.py
easy_tornado/filtering.py
easy_tornado/functional.py
easy_tornado/invoking.py
easy_tornado/suitcase.py
easy_tornado/tookit/__init__.py
easy_tornado/tookit/retriever.py
easy_tornado/utility/__init__.py
easy_tornado/utility/collection.py
easy_tornado/utility/datetime.py
easy_tornado/utility/exception.py
easy_tornado/utility/filesystem.py
easy_tornado/utility/httpclient.py
easy_tornado/utility/printext.py
easy_tornado/utility/ratelimiter.py
easy_tornado/utility/runtime.py
easy_tornado/utility/stringext.py
easy_tornado/utility/validation.py
easy_tornado/utility/webext.py
easy_tornado/web/__init__.py
easy_tornado/web/web_application_handler.py
easy_tornado-0.7.17.dist-info/METADATA
easy_tornado-0.7.17.dist-info/WHEEL
easy_tornado-0.7.17.dist-info/top_level.txt
easy_tornado-0.7.17.dist-info/RECORD
