Metadata-Version: 2.4
Name: easy_tornado
Version: 0.7.17
Summary: A tornado based web framework and toolkit package
Home-page: https://artifacts.wshugen.cn/python/easy_tornado
Author: Wang Shugen
Author-email: wsg1107556314@163.com
Requires-Dist: tornado
Requires-Dist: decorator
Requires-Dist: six
Requires-Dist: urllib3
Requires-Dist: psutil
Requires-Dist: jsonlines
Dynamic: author
Dynamic: author-email
Dynamic: home-page
Dynamic: requires-dist
Dynamic: summary
